{
  "kind": "collectionType",
  "collectionName": "read_notigications",
  "info": {
    "singularName": "read-notigication",
    "pluralName": "read-notigications",
    "displayName": "Read notigication"
  },
  "options": {
    "draftAndPublish": true
  },
  "attributes": {
    "users_permissions_user": {
      "type": "relation",
      "relation": "oneToOne",
      "target": "plugin::users-permissions.user"
    },
    "user_notigication": {
      "type": "relation",
      "relation": "oneToOne",
      "target": "api::user-notigication.user-notigication"
    },
    "sity_notification": {
      "type": "relation",
      "relation": "oneToOne",
      "target": "api::sity-notification.sity-notification"
    }
  }
}
